pypup/__init__.py
pypup/pypup.py
pypup/templates/aggrid.html
pypup/templates/bootstrap.html
pypup/templates/signin.html
pypup/templates/test.html
pypup/templates/tmp.html
pypup-0.0.3.dist-info/LICENSE
pypup-0.0.3.dist-info/METADATA
pypup-0.0.3.dist-info/WHEEL
pypup-0.0.3.dist-info/top_level.txt
pypup-0.0.3.dist-info/RECORD
