Metadata-Version: 2.1
Name: pypup
Version: 0.0.3
Summary: Build web apps using just Python
Author-email: Ashish Singal <ashish.singal1@gmail.com>
License: MIT License
Project-URL: Homepage, https://github.com/pypup/pypup
Keywords: pypup
Classifier: License :: OSI Approved :: MIT License
Classifier: Programming Language :: Python
Classifier: Programming Language :: Python :: 3
Requires-Python: >=3.9
License-File: LICENSE
Requires-Dist: flask
Requires-Dist: sqlalchemy
Provides-Extra: dev
